oryks_google_oauth/__init__.py
oryks_google_oauth/oauth.py
oryks_google_oauth/scopes.py
oryks_google_oauth-0.1.2.dist-info/LICENSE
oryks_google_oauth-0.1.2.dist-info/METADATA
oryks_google_oauth-0.1.2.dist-info/WHEEL
oryks_google_oauth-0.1.2.dist-info/top_level.txt
oryks_google_oauth-0.1.2.dist-info/RECORD
