Metadata-Version: 2.1
Name: oryks-google-oauth
Version: 0.1.2
Summary: A python library for authenticating requests for various google services including ``gmail``, ``youtube``, ``drive`` and ``calendar``.
Home-page: https://youtube-wrapper.readthedocs.io/en/latest/index.html
Author: Lyle Okoth
Author-email: lyceokoth@gmail.com
License: MIT
Keywords: google-auth
Platform: UNKNOWN
Classifier: Intended Audience :: Developers
Classifier: License :: OSI Approved :: MIT License
Classifier: Programming Language :: Python
Classifier: Programming Language :: Python :: 3
Classifier: Programming Language :: Python :: 3.10
Classifier: Programming Language :: Python :: 3.11
Classifier: Operating System :: OS Independent
License-File: LICENSE
Requires-Dist: google-api-python-client
Requires-Dist: google-auth-oauthlib
Requires-Dist: pydantic
Requires-Dist: pydantic-settings
